{
  "appInfo" : {
    "build" : "232.10335.12",
    "buildDate" : "2024-09-05T12:31:45.829Z[UTC]",
    "productCode" : "IC",
    "generated" : "2025-04-04T10:12:00.190912Z",
    "os" : "macOS 15.3.2",
    "runtime" : "JetBrains s.r.o. 17.0.12 17.0.12+7-b1000.54"
  },
  "runtimeInfo" : {
    "maxMemory" : 2147483648,
    "numberOfProcessors" : 8,
    "maxNumberOfIndexingThreads" : 7,
    "maxSizeOfFileForIntelliSense" : 2560000,
    "maxSizeOfFileForContentLoading" : 20971520
  },
  "type" : "Scanning",
  "projectIndexingActivityHistory" : {
    "projectName" : "untitled1",
    "times" : {
      "scanningReason" : "changes in: \"Module 'untitled1.main' (all roots)\", \"Module 'untitled1.test' (all roots)\", \"JDK corretto-21 /Users/Andjelina.Maksimovic/Library/Java/JavaVirtualMachines/corretto-21.0.6/Contents/Home\", \"Library Gradle: org.apiguardian:apiguardian-api:1.1.2 (#1 class roots, #1 source roots)\", \"Library Gradle: org.junit.jupiter:junit-jupiter-api:5.10.0 (#1 class roots, #1 source roots)\", \"Library Gradle: org.junit.jupiter:junit-jupiter-engine:5.10.0 (#1 class roots, #1 source roots)\", \"Library Gradle: org.junit.jupiter:junit-jupiter-params:5.10.0 (#1 class roots, #1 source roots)\", \"Library Gradle: org.junit.jupiter:junit-jupiter:5.10.0 (#1 class roots, #1 source roots)\", \"Library Gradle: org.junit.platform:junit-platform-commons:1.10.0 (#1 class roots, #1 source roots)\", \"Library Gradle: org.junit.platform:junit-platform-engine:1.10.0 (#1 class roots, #1 source roots)\" and 1 iterators more",
      "scanningType" : "PARTIAL",
      "scanningId" : 1,
      "creatingIteratorsTime" : 1000,
      "collectingIndexableFilesTime" : 636301000,
      "delayedPushPropertiesStageTime" : 5000,
      "indexExtensionsTime" : 17838363,
      "dumbModeStart" : "2025-04-04T10:11:59.553462Z",
      "dumbWallTimeWithPauses" : 637067000,
      "dumbWallTimeWithoutPauses" : 637067000,
      "updatingStart" : "2025-04-04T10:11:59.553273Z",
      "updatingEnd" : "2025-04-04T10:12:00.190529Z",
      "totalWallTimeWithPauses" : 637260541,
      "wallTimeOnPause" : 0,
      "wasInterrupted" : false,
      "totalWallTimeWithoutPauses" : 637260541
    },
    "fileCount" : {
      "numberOfFileProviders" : 11,
      "numberOfScannedFiles" : 45774,
      "numberOfFilesIndexedByInfrastructureExtensionsDuringScan" : 0,
      "numberOfFilesScheduledForIndexingAfterScan" : 1357
    },
    "scanningStatistics" : [ {
      "providerName" : "JDK corretto-21 /Users/Andjelina.Maksimovic/Library/Java/JavaVirtualMachines/corretto-21.0.6/Contents/Home",
      "numberOfScannedFiles" : 44417,
      "numberOfSkippedFiles" : 0,
      "numberOfFilesForIndexing" : 0,
      "numberOfFilesFullyIndexedByInfrastructureExtensions" : 0,
      "filesFullyIndexedByInfrastructureExtensions" : [ ],
      "statusTime" : 509198017,
      "scanningTime" : 525964603,
      "timeProcessingUpToDateFiles" : 0,
      "timeUpdatingContentLessIndexes" : 2475907,
      "timeIndexingWithoutContentViaInfrastructureExtension" : 0,
      "roots" : [ ]
    }, {
      "providerName" : "Library Gradle: org.junit.jupiter:junit-jupiter-params:5.10.0 (#1 class roots, #1 source roots)",
      "numberOfScannedFiles" : 414,
      "numberOfSkippedFiles" : 0,
      "numberOfFilesForIndexing" : 414,
      "numberOfFilesFullyIndexedByInfrastructureExtensions" : 0,
      "filesFullyIndexedByInfrastructureExtensions" : [ ],
      "statusTime" : 40276965,
      "scanningTime" : 51094124,
      "timeProcessingUpToDateFiles" : 0,
      "timeUpdatingContentLessIndexes" : 22168925,
      "timeIndexingWithoutContentViaInfrastructureExtension" : 4164313,
      "roots" : [ ]
    }, {
      "providerName" : "Library Gradle: org.junit.jupiter:junit-jupiter-api:5.10.0 (#1 class roots, #1 source roots)",
      "numberOfScannedFiles" : 336,
      "numberOfSkippedFiles" : 0,
      "numberOfFilesForIndexing" : 336,
      "numberOfFilesFullyIndexedByInfrastructureExtensions" : 0,
      "filesFullyIndexedByInfrastructureExtensions" : [ ],
      "statusTime" : 29363732,
      "scanningTime" : 43651667,
      "timeProcessingUpToDateFiles" : 0,
      "timeUpdatingContentLessIndexes" : 16483570,
      "timeIndexingWithoutContentViaInfrastructureExtension" : 2749747,
      "roots" : [ ]
    }, {
      "providerName" : "Library Gradle: org.junit.jupiter:junit-jupiter-engine:5.10.0 (#1 class roots, #1 source roots)",
      "numberOfScannedFiles" : 235,
      "numberOfSkippedFiles" : 0,
      "numberOfFilesForIndexing" : 235,
      "numberOfFilesFullyIndexedByInfrastructureExtensions" : 0,
      "filesFullyIndexedByInfrastructureExtensions" : [ ],
      "statusTime" : 32081044,
      "scanningTime" : 41585458,
      "timeProcessingUpToDateFiles" : 0,
      "timeUpdatingContentLessIndexes" : 19415235,
      "timeIndexingWithoutContentViaInfrastructureExtension" : 2829420,
      "roots" : [ ]
    }, {
      "providerName" : "Library Gradle: org.junit.platform:junit-platform-engine:1.10.0 (#1 class roots, #1 source roots)",
      "numberOfScannedFiles" : 240,
      "numberOfSkippedFiles" : 0,
      "numberOfFilesForIndexing" : 240,
      "numberOfFilesFullyIndexedByInfrastructureExtensions" : 0,
      "filesFullyIndexedByInfrastructureExtensions" : [ ],
      "statusTime" : 29007920,
      "scanningTime" : 33083170,
      "timeProcessingUpToDateFiles" : 0,
      "timeUpdatingContentLessIndexes" : 17976119,
      "timeIndexingWithoutContentViaInfrastructureExtension" : 2572998,
      "roots" : [ ]
    }, {
      "providerName" : "Library Gradle: org.junit.platform:junit-platform-commons:1.10.0 (#1 class roots, #1 source roots)",
      "numberOfScannedFiles" : 93,
      "numberOfSkippedFiles" : 0,
      "numberOfFilesForIndexing" : 93,
      "numberOfFilesFullyIndexedByInfrastructureExtensions" : 0,
      "filesFullyIndexedByInfrastructureExtensions" : [ ],
      "statusTime" : 20597537,
      "scanningTime" : 30474668,
      "timeProcessingUpToDateFiles" : 0,
      "timeUpdatingContentLessIndexes" : 10910368,
      "timeIndexingWithoutContentViaInfrastructureExtension" : 1764840,
      "roots" : [ ]
    }, {
      "providerName" : "Library Gradle: org.apiguardian:apiguardian-api:1.1.2 (#1 class roots, #1 source roots)",
      "numberOfScannedFiles" : 9,
      "numberOfSkippedFiles" : 0,
      "numberOfFilesForIndexing" : 9,
      "numberOfFilesFullyIndexedByInfrastructureExtensions" : 0,
      "filesFullyIndexedByInfrastructureExtensions" : [ ],
      "statusTime" : 11616916,
      "scanningTime" : 22246249,
      "timeProcessingUpToDateFiles" : 0,
      "timeUpdatingContentLessIndexes" : 4794332,
      "timeIndexingWithoutContentViaInfrastructureExtension" : 227793,
      "roots" : [ ]
    }, {
      "providerName" : "Library Gradle: org.junit.jupiter:junit-jupiter:5.10.0 (#1 class roots, #1 source roots)",
      "numberOfScannedFiles" : 8,
      "numberOfSkippedFiles" : 0,
      "numberOfFilesForIndexing" : 8,
      "numberOfFilesFullyIndexedByInfrastructureExtensions" : 0,
      "filesFullyIndexedByInfrastructureExtensions" : [ ],
      "statusTime" : 3211917,
      "scanningTime" : 13199378,
      "timeProcessingUpToDateFiles" : 0,
      "timeUpdatingContentLessIndexes" : 1873378,
      "timeIndexingWithoutContentViaInfrastructureExtension" : 168961,
      "roots" : [ ]
    }, {
      "providerName" : "Library Gradle: org.opentest4j:opentest4j:1.3.0 (#1 class roots, #1 source roots)",
      "numberOfScannedFiles" : 21,
      "numberOfSkippedFiles" : 0,
      "numberOfFilesForIndexing" : 21,
      "numberOfFilesFullyIndexedByInfrastructureExtensions" : 0,
      "filesFullyIndexedByInfrastructureExtensions" : [ ],
      "statusTime" : 6089541,
      "scanningTime" : 7309833,
      "timeProcessingUpToDateFiles" : 0,
      "timeUpdatingContentLessIndexes" : 3048332,
      "timeIndexingWithoutContentViaInfrastructureExtension" : 431332,
      "roots" : [ ]
    }, {
      "providerName" : "Module 'untitled1.main' (all roots)",
      "numberOfScannedFiles" : 1,
      "numberOfSkippedFiles" : 0,
      "numberOfFilesForIndexing" : 1,
      "numberOfFilesFullyIndexedByInfrastructureExtensions" : 0,
      "filesFullyIndexedByInfrastructureExtensions" : [ ],
      "statusTime" : 3000375,
      "scanningTime" : 4943042,
      "timeProcessingUpToDateFiles" : 0,
      "timeUpdatingContentLessIndexes" : 542,
      "timeIndexingWithoutContentViaInfrastructureExtension" : 2928959,
      "roots" : [ ]
    }, {
      "providerName" : "Module 'untitled1.test' (all roots)",
      "numberOfScannedFiles" : 0,
      "numberOfSkippedFiles" : 0,
      "numberOfFilesForIndexing" : 0,
      "numberOfFilesFullyIndexedByInfrastructureExtensions" : 0,
      "filesFullyIndexedByInfrastructureExtensions" : [ ],
      "statusTime" : 0,
      "scanningTime" : 1083083,
      "timeProcessingUpToDateFiles" : 0,
      "timeUpdatingContentLessIndexes" : 0,
      "timeIndexingWithoutContentViaInfrastructureExtension" : 0,
      "roots" : [ ]
    } ]
  }
}